sxhkhm/__init__.py
sxhkhm-0.4.4.data/scripts/sxhkhmenu
sxhkhm-0.4.4.dist-info/LICENSE
sxhkhm-0.4.4.dist-info/METADATA
sxhkhm-0.4.4.dist-info/WHEEL
sxhkhm-0.4.4.dist-info/entry_points.txt
sxhkhm-0.4.4.dist-info/top_level.txt
sxhkhm-0.4.4.dist-info/RECORD
