Metadata-Version: 2.1
Name: sxhkhm
Version: 0.4.4
Summary: HotKey helper for sxhkd
Home-page: https://github.com/fiskhest/sxhkd-helper-menu
Author: Johan Radivoj
Author-email: johan+sxhkhm@radivoj.se
License: UNKNOWN
Platform: UNKNOWN
Classifier: Programming Language :: Python :: 3
Classifier: License :: OSI Approved :: MIT License
Classifier: Operating System :: OS Independent
Requires-Python: >=3.6
